{
  "changelogDate": "20220413150618",
  "dto": "mapstruct",
  "fields": [
    {
      "fieldName": "assetNumber",
      "fieldType": "String",
      "fieldValidateRules": ["required", "unique"]
    },
    {
      "fieldName": "assetTag",
      "fieldType": "String",
      "fieldValidateRules": ["required"]
    },
    {
      "fieldName": "assetDetails",
      "fieldType": "String"
    },
    {
      "fieldName": "assetCost",
      "fieldType": "BigDecimal",
      "fieldValidateRules": ["required"]
    },
    {
      "fieldName": "comments",
      "fieldType": "byte[]",
      "fieldTypeBlobContent": "any"
    },
    {
      "fieldName": "modelNumber",
      "fieldType": "String"
    },
    {
      "fieldName": "serialNumber",
      "fieldType": "String"
    },
    {
      "fieldName": "remarks",
      "fieldType": "byte[]",
      "fieldTypeBlobContent": "text"
    },
    {
      "fieldName": "capitalizationDate",
      "fieldType": "LocalDate",
      "fieldValidateRules": ["required"]
    },
    {
      "fieldName": "historicalCost",
      "fieldType": "BigDecimal"
    },
    {
      "fieldName": "registrationDate",
      "fieldType": "LocalDate"
    }
  ],
  "incrementalChangelog": false,
  "jpaMetamodelFiltering": true,
  "name": "AssetRegistration",
  "pagination": "pagination",
  "readOnly": false,
  "relationships": [
    {
      "otherEntityField": "description",
      "otherEntityName": "placeholder",
      "otherEntityRelationshipName": "assetRegistration",
      "ownerSide": true,
      "relationshipName": "placeholder",
      "relationshipType": "many-to-many"
    },
    {
      "otherEntityField": "assetCategoryName",
      "otherEntityName": "assetCategory",
      "relationshipName": "assetCategory",
      "relationshipType": "many-to-one",
      "relationshipValidateRules": ["required"]
    },
    {
      "otherEntityField": "dealerName",
      "otherEntityName": "dealer",
      "relationshipName": "dealer",
      "relationshipType": "many-to-one",
      "relationshipValidateRules": ["required"]
    },
    {
      "relationshipName": "settlementCurrency",
      "otherEntityName": "settlementCurrency",
      "relationshipType": "many-to-one",
      "otherEntityField": "iso4217CurrencyCode"
    },
    {
      "relationshipName": "mainServiceOutlet",
      "otherEntityName": "serviceOutlet",
      "relationshipType": "many-to-one",
      "otherEntityField": "outletCode"
    },
    {
      "relationshipName": "acquiringTransaction",
      "otherEntityName": "settlement",
      "relationshipType": "many-to-one",
      "relationshipValidateRules": ["required"],
      "otherEntityField": "paymentNumber"
    }
  ],
  "service": "serviceImpl"
}
